setup.py
aiff_kit/__init__.py
aiff_kit/system.py
aiff_kit.egg-info/PKG-INFO
aiff_kit.egg-info/SOURCES.txt
aiff_kit.egg-info/dependency_links.txt
aiff_kit.egg-info/top_level.txt