Metadata-Version: 2.1
Name: aiff-kit
Version: 0.0.1
Summary: a library for extract the information
Home-page: UNKNOWN
Author: zdcao
Author-email: zdcao121@qq.com
License: MIT License
Keywords: aiff
Platform: any
